ExchangeComparison/__init__.py
ExchangeComparison/exchange.py
ExchangeComparison-0.1.0.dist-info/LICENSE
ExchangeComparison-0.1.0.dist-info/METADATA
ExchangeComparison-0.1.0.dist-info/WHEEL
ExchangeComparison-0.1.0.dist-info/top_level.txt
ExchangeComparison-0.1.0.dist-info/RECORD
