Metadata-Version: 2.1
Name: ExchangeComparison
Version: 0.1.0
Summary: The programme is designed to find the lower period of similar movements.
Home-page: https://github.com/masa2122/similar_rates
Download-URL: https://github.com/masa2122/similar_rates
Author: Katsumori Okazaki
Maintainer: Katsumori Okazaki
License: MIT
Keywords: exchange money order
Classifier: Development Status :: 3 - Alpha
Classifier: Intended Audience :: Developers
Classifier: License :: OSI Approved :: MIT License
Classifier: Programming Language :: Python :: 3
Classifier: Programming Language :: Python :: 3.6
Classifier: Programming Language :: Python :: 3.7
Classifier: Programming Language :: Python :: 3.8
Classifier: Programming Language :: Python :: 3.9
License-File: LICENSE
Requires-Dist: numpy
Requires-Dist: matplotlib
Requires-Dist: yfinance
